mi_paquete/__init__.py
wsxtext009/__init__.py
wsxtext009-0.1.0.dist-info/METADATA
wsxtext009-0.1.0.dist-info/WHEEL
wsxtext009-0.1.0.dist-info/top_level.txt
wsxtext009-0.1.0.dist-info/RECORD
